{
    "configurations": [
        {
            "name": "Win32",
            "includePath": [
                "${workspaceFolder}/**",
                "${workspaceFolder}/embed/common",
                "${workspaceFolder}/embed/common/event",
                "${workspaceFolder}/embed/lower_device/include",
                "${workspaceFolder}/embed/logger_tool/include",
                "${workspaceFolder}/embed/main_process/mb/include"
            ],
            "defines": [
                "_DEBUG",
                "UNICODE",
                "_UNICODE",
                "__ARM_PCS_VFP",
                "MODULE_DEFINE_MQTT",
                "USE_OPENCV=1",
                "CONFIG_CPU_FREQ=y"
            ],
            "windowsSdkVersion": "8.1",
            "compilerPath": "D:/Software/Visual Studio 2015/VC/bin/cl.exe",
            "cStandard": "c11",
            "cppStandard": "c++17",
            "intelliSenseMode": "msvc-x64"
        }
    ],
    "version": 4
}